apigentools/__init__.py
apigentools/cli.py
apigentools/config.py
apigentools/constants.py
apigentools/errors.py
apigentools/utils.py
apigentools/version.py
apigentools/commands/__init__.py
apigentools/commands/command.py
apigentools/commands/generate.py
apigentools/commands/init.py
apigentools/commands/list_config.py
apigentools/commands/merge.py
apigentools/commands/push.py
apigentools/commands/split.py
apigentools/commands/templates.py
apigentools/commands/test.py
apigentools/commands/validate.py
tests/integration/__init__.py
tests/integration/test_examples.py
tests/integration/test_init.py
tests/integration/test_versions.py
tests/unit/__init__.py
tests/unit/test_config.py
tests/unit/test_push.py
tests/unit/test_utils.py
tests/unit/fixtures/good_config_yaml.yaml
apigentools-1.6.6.dist-info/LICENSE
apigentools-1.6.6.dist-info/LICENSE-3rdparty.csv
apigentools-1.6.6.dist-info/METADATA
apigentools-1.6.6.dist-info/WHEEL
apigentools-1.6.6.dist-info/entry_points.txt
apigentools-1.6.6.dist-info/top_level.txt
apigentools-1.6.6.dist-info/RECORD
