Metadata-Version: 2.1
Name: apigentools
Version: 1.6.6
Summary: Tooling for generation of API clients using openapi-generator
Home-page: https://github.com/DataDog/apigentools
Author: Datadog
Author-email: packages@datadoghq.com
License: BSD 3-clause
Project-URL: Bug Tracker, https://github.com/DataDog/apigentools/issues
Project-URL: Documentation, https://apigentools.readthedocs.io/en/latest/
Project-URL: Source Code, https://github.com/DataDog/apigentools
Keywords: openapi,api,client,openapi-generator
Platform: any
Classifier: Development Status :: 4 - Beta
Classifier: Intended Audience :: Developers
Classifier: License :: OSI Approved :: BSD License
Classifier: Operating System :: OS Independent
Classifier: Programming Language :: Python :: 3.9
Classifier: Programming Language :: Python :: 3.10
Requires-Python: >=3.7
License-File: LICENSE
License-File: LICENSE-3rdparty.csv
Requires-Dist: chevron >=0.14.0
Requires-Dist: click >=8.0.0
Requires-Dist: jsonpath-ng >=1.5.1
Requires-Dist: PyYAML <7.0.0,>=5.4.1
Requires-Dist: packaging >=21.3
Requires-Dist: pydantic <2,>=1.9.0
Provides-Extra: tests
Requires-Dist: black >=20.8b1 ; extra == 'tests'
Requires-Dist: flexmock <0.11,>=0.10.4 ; extra == 'tests'
Requires-Dist: pytest >=5.2.4 ; extra == 'tests'
Requires-Dist: pytest-cov ; extra == 'tests'
Requires-Dist: pytest-black ; extra == 'tests'
Requires-Dist: pytest-console-scripts ; extra == 'tests'
